pitfall/__init__.py
pitfall/actions.py
pitfall/config.py
pitfall/core.py
pitfall/exceptions.py
pitfall/plugins.py
pitfall/project.py
pitfall/stack.py
pitfall/state.py
pitfall/utils.py
pitfall/helpers/__init__.py
pitfall/helpers/aws/__init__.py
pitfall/helpers/aws/iam.py
pitfall/helpers/aws/utils.py
pitfall-0.0.4.dist-info/LICENSE
pitfall-0.0.4.dist-info/METADATA
pitfall-0.0.4.dist-info/WHEEL
pitfall-0.0.4.dist-info/top_level.txt
pitfall-0.0.4.dist-info/RECORD
