Metadata-Version: 2.1
Name: pitfall
Version: 0.0.4
Summary: An integration testing framework for Pulumi Infrastructure as Code
Home-page: http://github.com/bincyber/pitfall
Author: @bincyber
Author-email: bincyber@users.noreply.github.com
License: Apache
Keywords: infrastructure-as-code testing devops pulumi
Platform: any
Classifier: Development Status :: 3 - Alpha
Classifier: Environment :: Console
Classifier: Intended Audience :: Developers
Classifier: Intended Audience :: System Administrators
Classifier: Natural Language :: English
Classifier: License :: OSI Approved :: Apache Software License
Classifier: Operating System :: MacOS
Classifier: Operating System :: POSIX
Classifier: Operating System :: Unix
Classifier: Programming Language :: Python
Classifier: Programming Language :: Python :: 3.7
Classifier: Programming Language :: Python :: 3.8
Classifier: Programming Language :: Python :: Implementation :: CPython
Classifier: Topic :: Software Development :: Testing
Classifier: Topic :: Software Development :: Quality Assurance
Classifier: Topic :: System :: Systems Administration
Requires-Python: >=3.7
Requires-Dist: anytree (==2.7.2)
Requires-Dist: boto3 (==1.10.9)
Requires-Dist: pycryptodomex (==3.9.0)
Requires-Dist: PyYAML (==5.1.2)
